vlmrun/hub/catalog.yaml
vlmrun/hub/constants.py
vlmrun/hub/dataset.py
vlmrun/hub/registry.py
vlmrun/hub/utils.py
vlmrun/hub/version.py
vlmrun/hub/schemas/__init__.py
vlmrun/hub/schemas/accounting/w2_form.py
vlmrun/hub/schemas/aerospace/remote_sensing.py
vlmrun/hub/schemas/contrib/catalog.yaml
vlmrun/hub/schemas/contrib/accounting/form_1040_tax_statement.py
vlmrun/hub/schemas/contrib/accounting/form_payslip.py
vlmrun/hub/schemas/contrib/document/bank_check.py
vlmrun/hub/schemas/contrib/document/business_card.py
vlmrun/hub/schemas/contrib/document/form_work_order.py
vlmrun/hub/schemas/contrib/document/insurance_claim.py
vlmrun/hub/schemas/contrib/document/request_for_proposal.py
vlmrun/hub/schemas/contrib/document/us_passport.py
vlmrun/hub/schemas/contrib/document/india/aadhaar_card.py
vlmrun/hub/schemas/contrib/document/india/pan_card.py
vlmrun/hub/schemas/contrib/finance/balance_sheet.py
vlmrun/hub/schemas/contrib/food/nutrition_facts_label.py
vlmrun/hub/schemas/contrib/healthcare/pathology_report.py
vlmrun/hub/schemas/contrib/logistics/bill_of_lading.py
vlmrun/hub/schemas/contrib/media/nba_game_state.py
vlmrun/hub/schemas/contrib/media/nfl_game_state.py
vlmrun/hub/schemas/contrib/real_estate/lease_agreement.py
vlmrun/hub/schemas/contrib/social/twitter_card.py
vlmrun/hub/schemas/document/bank_statement.py
vlmrun/hub/schemas/document/invoice.py
vlmrun/hub/schemas/document/receipt.py
vlmrun/hub/schemas/document/resume.py
vlmrun/hub/schemas/document/us_drivers_license.py
vlmrun/hub/schemas/document/utility_bill.py
vlmrun/hub/schemas/healthcare/hipaa_release.py
vlmrun/hub/schemas/healthcare/medical_insurance_card.py
vlmrun/hub/schemas/media/tv_news.py
vlmrun/hub/schemas/retail/ecommerce_product_caption.py
vlmrun/hub/schemas/retail/product_catalog.py
vlmrun/hub/server/__init__.py
vlmrun/hub/server/app.py
vlmrun/hub/server/routes.py
vlmrun_hub-0.1.35.dist-info/licenses/LICENSE
vlmrun_hub-0.1.35.dist-info/METADATA
vlmrun_hub-0.1.35.dist-info/WHEEL
vlmrun_hub-0.1.35.dist-info/top_level.txt
vlmrun_hub-0.1.35.dist-info/RECORD
