Metadata-Version: 2.4
Name: vlmrun-hub
Version: 0.1.35
Summary: VLM Run Hub for various industry-specific schemas
Author-email: VLM Support <support@vlm.com>
License: Apache-2.0
Project-URL: homepage, https://github.com/vlm-run/vlmrun-hub
Project-URL: repository, https://github.com/vlm-run/vlmrun-hub
Project-URL: documentation, https://docs.vlm.run/hub
Classifier: Development Status :: 4 - Beta
Classifier: Programming Language :: Python
Classifier: Environment :: Console
Classifier: Intended Audience :: Developers
Classifier: Intended Audience :: Education
Classifier: Intended Audience :: Information Technology
Classifier: Intended Audience :: Science/Research
Classifier: Topic :: Software Development :: Libraries
Classifier: Topic :: Scientific/Engineering :: Artificial Intelligence
Classifier: Topic :: Scientific/Engineering :: Image Processing
Classifier: License :: OSI Approved :: Apache Software License
Classifier: Programming Language :: Python :: 3 :: Only
Classifier: Programming Language :: Python :: 3.9
Classifier: Programming Language :: Python :: 3.10
Classifier: Programming Language :: Python :: 3.11
Requires-Python: >=3.9
License-File: LICENSE
Requires-Dist: annotated-types>=0.7.0
Requires-Dist: datamodel-code-generator<=0.39.0,>=0.26.1
Requires-Dist: loguru>=0.7.3
Requires-Dist: Pillow>=10.2.0
Requires-Dist: pydantic<3,>=2.5
Requires-Dist: pydantic_core>=2.23.4
Requires-Dist: pydantic_yaml>=1.2.0
Requires-Dist: typing_extensions>=4.12.2
Provides-Extra: test
Requires-Dist: fastapi>=0.115.8; extra == "test"
Requires-Dist: httpx>=0.28.0; extra == "test"
Requires-Dist: instructor>=1.7.0; extra == "test"
Requires-Dist: openai>=1.58.1; extra == "test"
Requires-Dist: pandas>=2.1.1; extra == "test"
Requires-Dist: pre-commit>=4.0.1; extra == "test"
Requires-Dist: pytest>=8.3.4; extra == "test"
Requires-Dist: python-dotenv>=1.0.1; extra == "test"
Requires-Dist: requests>=2.32.3; extra == "test"
Requires-Dist: ruff>=0.2.2; extra == "test"
Requires-Dist: tqdm>=4.67.1; extra == "test"
Requires-Dist: twine>=6.0.1; extra == "test"
Requires-Dist: vlmrun[doc]>=0.1.14; extra == "test"
Provides-Extra: build
Requires-Dist: build>=1.2.2; extra == "build"
Requires-Dist: twine>=6.0.1; extra == "build"
Provides-Extra: extra
Requires-Dist: ollama>=0.4.4; extra == "extra"
Provides-Extra: server
Requires-Dist: fastapi>=0.115.8; extra == "server"
Requires-Dist: httpx>=0.28.0; extra == "server"
Requires-Dist: uvicorn[standard]>=0.34.0; extra == "server"
Provides-Extra: all
Requires-Dist: fastapi>=0.115.8; extra == "all"
Requires-Dist: httpx>=0.28.0; extra == "all"
Requires-Dist: instructor>=1.7.0; extra == "all"
Requires-Dist: openai>=1.58.1; extra == "all"
Requires-Dist: pandas>=2.1.1; extra == "all"
Requires-Dist: pre-commit>=4.0.1; extra == "all"
Requires-Dist: pytest>=8.3.4; extra == "all"
Requires-Dist: python-dotenv>=1.0.1; extra == "all"
Requires-Dist: requests>=2.32.3; extra == "all"
Requires-Dist: ruff>=0.2.2; extra == "all"
Requires-Dist: tqdm>=4.67.1; extra == "all"
Requires-Dist: twine>=6.0.1; extra == "all"
Requires-Dist: vlmrun[doc]>=0.1.14; extra == "all"
Requires-Dist: build>=1.2.2; extra == "all"
Requires-Dist: twine>=6.0.1; extra == "all"
Requires-Dist: ollama>=0.4.4; extra == "all"
Requires-Dist: fastapi>=0.115.8; extra == "all"
Requires-Dist: httpx>=0.28.0; extra == "all"
Requires-Dist: uvicorn[standard]>=0.34.0; extra == "all"
Dynamic: license-file
